CONTRIBUTORS
LICENSE
MANIFEST.in
README.rst
setup.py
bin/post-receive
bin/post-update
bin/pre-receive
bin/update
gitmesh/__init__.py
gitmesh/__main__.py
gitmesh/server.py
gitmesh/storage.py
gitmesh/version.txt
gitmesh.egg-info/PKG-INFO
gitmesh.egg-info/SOURCES.txt
gitmesh.egg-info/dependency_links.txt
gitmesh.egg-info/entry_points.txt
gitmesh.egg-info/requires.txt
gitmesh.egg-info/top_level.txt
tests/__init__.py
tests/conftest.py
tests/exit-failure.py
tests/exit-success.py
tests/pwd.py
tests/test_cli.py
tests/test_hooks.py
tests/test_main.py
tests/test_server.py
tests/test_storage.py
tests/test_version.py