Metadata-Version: 1.0
Name: gitmesh
Version: 0.3.0
Summary: Tools for building a Git server
Home-page: https://github.com/smartmob-project/gitmesh
Author: Andre Caron
Author-email: ac@smartmob.org
License: UNKNOWN
Platform: UNKNOWN
